pdf_nupper/__init__.py
pdf_nupper/cli.py
pdf_nupper/core.py
pdf_nupper-0.1.2.dist-info/LICENSE
pdf_nupper-0.1.2.dist-info/METADATA
pdf_nupper-0.1.2.dist-info/WHEEL
pdf_nupper-0.1.2.dist-info/entry_points.txt
pdf_nupper-0.1.2.dist-info/top_level.txt
pdf_nupper-0.1.2.dist-info/RECORD
