Metadata-Version: 2.1
Name: pdf-nupper
Version: 0.1.2
Summary: A command-line tool for n-upping PDF files (e.g., combining 2 pages into one) for printing purposes.
Author-email: Thameera Senanayaka <me@thameera.com>
Project-URL: Homepage, https://github.com/thameera/pdf-nupper
Project-URL: Bug Tracker, https://github.com/thameera/pdf-nupper/issues
Keywords: PDF,n-up,combine,printing
Classifier: Programming Language :: Python :: 3
Classifier: License :: OSI Approved :: MIT License
Classifier: Operating System :: OS Independent
Requires-Python: >=3.6
License-File: LICENSE
Requires-Dist: pypdf>=4.3.0
